{
  "title": "Quizzes",
  "hero": {
    "title": "Questions Generator",
    "description": "Enter a passage of text, and let our generator create a list of interactive and insightful questions for you to use. Perfect for quizzes, exams, or just expanding knowledge!"
  },
  "generate-question-form": {
    "input-placeholder": "Type your message here",
    "button": "Send",
    "switch": "File / Text",
    "dnd": {
      "default": "Drag and drop your file here or click to browse",
      "active": "Drop the file here...",
      "disabled": "Only one file is allowed",
      "remove": "Remove"
    }
  },
  "questions": {
    "title": "Generated Questions",
    "description": "Here are the questions generated from your input:"
  }
}
